robot_mobile/__init__.py
robot_mobile/index.py
robot_mobile/mobile_inspector.py
robot_mobile/mobile_inspector_main.py
robot_mobile/uidumplib.py
robot_mobile-0.3.0.dist-info/METADATA
robot_mobile-0.3.0.dist-info/WHEEL
robot_mobile-0.3.0.dist-info/RECORD
